data_ecosystem_python/__main__.py
data_ecosystem_python/alation_service/__init__.py
data_ecosystem_python/alation_service/custom_fields.py
data_ecosystem_python/alation_service/datasource.py
data_ecosystem_python/alation_service/db_column.py
data_ecosystem_python/alation_service/db_schema.py
data_ecosystem_python/alation_service/db_table.py
data_ecosystem_python/alation_service/endpoint.py
data_ecosystem_python/alation_service/excel_manifest.py
data_ecosystem_python/alation_service/execution_session.py
data_ecosystem_python/alation_service/id_finder.py
data_ecosystem_python/alation_service/json_manifest.py
data_ecosystem_python/alation_service/query.py
data_ecosystem_python/alation_service/tags.py
data_ecosystem_python/alation_service/token.py
data_ecosystem_python/alation_service/tokenendpoint.py
data_ecosystem_python/alation_service/user.py
data_ecosystem_python/app.py
data_ecosystem_python/app_startup.py
data_ecosystem_python/az_client_service/__init__.py
data_ecosystem_python/az_client_service/az_client.py
data_ecosystem_python/az_client_service/azd_client.py
data_ecosystem_python/az_key_vault_service/__init__.py
data_ecosystem_python/az_key_vault_service/az_key_vault.py
data_ecosystem_python/az_storage_service/__init__.py
data_ecosystem_python/az_storage_service/az_storage_queue.py
data_ecosystem_python/cdc_admin_service/__init__.py
data_ecosystem_python/cdc_admin_service/environment_logging.py
data_ecosystem_python/cdc_admin_service/environment_tracing.py
data_ecosystem_python/cdc_admin_service/sequence_diagram.py
data_ecosystem_python/cdc_security_service/__init__.py
data_ecosystem_python/cdc_security_service/security_base64.py
data_ecosystem_python/cdc_security_service/security_core.py
data_ecosystem_python/cdc_self_service/__init__.py
data_ecosystem_python/cdc_self_service/dataset_metadata.py
data_ecosystem_python/cdc_self_service/environment_metadata.py
data_ecosystem_python/cdc_self_service/job_metadata.py
data_ecosystem_python-202308.0.25.dist-info/METADATA
data_ecosystem_python-202308.0.25.dist-info/WHEEL
data_ecosystem_python-202308.0.25.dist-info/entry_points.txt
data_ecosystem_python-202308.0.25.dist-info/RECORD
